ircelsos/__init__.py
ircelsos/__main__.py
ircelsos/_stations.py
ircelsos/interactive.py
ircelsos/main.py
ircelsos/metadata.py
ircelsos/parser.py
ircelsos/query_ircelsos.py
ircelsos/sos.py
ircelsos/util.py
ircelsos-0.2.2.dist-info/DESCRIPTION.rst
ircelsos-0.2.2.dist-info/METADATA
ircelsos-0.2.2.dist-info/RECORD
ircelsos-0.2.2.dist-info/WHEEL
ircelsos-0.2.2.dist-info/entry_points.txt
ircelsos-0.2.2.dist-info/metadata.json
ircelsos-0.2.2.dist-info/pbr.json
ircelsos-0.2.2.dist-info/top_level.txt
