Metadata-Version: 2.0
Name: ircelsos
Version: 0.2.2
Summary: Downloading air quality data from the SOS of IRCEL - CELINE
Home-page: https://github.com/jorisvandenbossche/ircelsos
Author: Joris Van den Bossche
Author-email: jorisvandenbossche@gmail.com
License: BSD
Platform: UNKNOWN
Requires-Dist: owslib (==0.9.0)
Requires-Dist: six
